MANIFEST.in
README.md
setup.py
aioflow/__init__.py
aioflow/helpers.py
aioflow/middlewareabc.py
aioflow/mixins.py
aioflow/pipeline.py
aioflow/service.py
aioflow.egg-info/PKG-INFO
aioflow.egg-info/SOURCES.txt
aioflow.egg-info/dependency_links.txt
aioflow.egg-info/requires.txt
aioflow.egg-info/top_level.txt
aioflow/middleware/__init__.py
aioflow/middleware/redis_meddleware.py
tests/__init__.py
tests/test_helpers.py
tests/test_mixins.py
tests/test_pipeline.py
tests/test_service.py