Metadata-Version: 2.1
Name: aioflow
Version: 0.0.9
Summary: A simple workflow implementation using asyncio.
Home-page: UNKNOWN
Author: Andrey Lemets
Author-email: a.a.lemets@gmail.com
License: MIT License
Platform: UNKNOWN
Provides-Extra: aioredis
Provides-Extra: tests
